echowuhao/__init__.py
echowuhao/auto_commit/__init__.py
echowuhao/auto_commit/command_line.py
echowuhao/chat/chat.py
echowuhao/chat/choose_model.py
echowuhao/docker/docker_manual_proxy.py
echowuhao-0.4.8.dist-info/METADATA
echowuhao-0.4.8.dist-info/WHEEL
echowuhao-0.4.8.dist-info/entry_points.txt
echowuhao-0.4.8.dist-info/RECORD
