Metadata-Version: 2.4
Name: echowuhao
Version: 0.4.8
Summary: Personal tools
Requires-Python: >=3.8
Requires-Dist: openai>=1.44.1
Requires-Dist: requests>=2.32.3
Requires-Dist: rich>=13.8.0
